revChatGPT/V1.py
revChatGPT/V3.py
revChatGPT/__init__.py
revChatGPT/__main__.py
revChatGPT/typings.py
revChatGPT/utils.py
revChatGPT/version.py
revChatGPT/config/enable_internet.json
GPT_wrapper-6.8.6.dist-info/LICENSE
GPT_wrapper-6.8.6.dist-info/METADATA
GPT_wrapper-6.8.6.dist-info/WHEEL
GPT_wrapper-6.8.6.dist-info/top_level.txt
GPT_wrapper-6.8.6.dist-info/RECORD
